ccsds_ndm/__init__.py
ccsds_ndm/__init__.pyi
ccsds_ndm/ccsds_ndm.abi3.so
ccsds_ndm_py-0.0.3.dist-info/METADATA
ccsds_ndm_py-0.0.3.dist-info/WHEEL
ccsds_ndm_py-0.0.3.dist-info/RECORD
