Metadata-Version: 2.4
Name: ccsds-ndm-py
Version: 0.0.3
Classifier: Development Status :: 4 - Beta
Classifier: Intended Audience :: Science/Research
Classifier: License :: OSI Approved :: Mozilla Public License 2.0 (MPL 2.0)
Classifier: Programming Language :: Rust
Classifier: Programming Language :: Python :: 3
Classifier: Programming Language :: Python :: 3.9
Classifier: Programming Language :: Python :: 3.10
Classifier: Programming Language :: Python :: 3.11
Classifier: Programming Language :: Python :: 3.12
Classifier: Programming Language :: Python :: 3.13
Classifier: Topic :: Scientific/Engineering :: Astronomy
Classifier: Topic :: Scientific/Engineering :: Physics
Requires-Dist: numpy>=1.16.0
Summary: Parse and generate CCSDS Navigation Data Messages (NDM) in KVN and XML formats
Keywords: ccsds,ndm,space,orbit,astrodynamics,ephemeris
Author-email: Jochim Maene <jochim.maene+github@gmail.com>
License-Expression: MPL-2.0
Requires-Python: >=3.9
Project-URL: Changelog, https://github.com/JochimMaene/ccsds-ndm/releases
Project-URL: Documentation, https://jochimmaene.github.io/ccsds-ndm
Project-URL: Homepage, https://github.com/JochimMaene/ccsds-ndm
Project-URL: Issues, https://github.com/JochimMaene/ccsds-ndm/issues
Project-URL: Repository, https://github.com/JochimMaene/ccsds-ndm
